pyepoet/__init__.py
pyepoet/pyepoet.py
pyepoet-0.1.3.dist-info/METADATA
pyepoet-0.1.3.dist-info/WHEEL
pyepoet-0.1.3.dist-info/top_level.txt
pyepoet-0.1.3.dist-info/RECORD
