Metadata-Version: 2.1
Name: pyepoet
Version: 0.1.3
Summary: 电子诗人Python版
Home-page: UNKNOWN
Author: Time Studio
Author-email: sjgzszg@163.com
License: UNKNOWN
Platform: UNKNOWN
